Metadata-Version: 2.1
Name: pychordpro
Version: 0.1
Summary: A simple package to create, edit, compile files in the ChordPro file format.
Home-page: https://github.com/FraKappa/pychordpro
Author: Kappa
Author-email: f.cappetti.05@gmail.com
License: MIT
Download-URL: https://github.com/FraKappa/pychordpro/archive/v_01.tar.gz
Keywords: chordpro,music
Platform: UNKNOWN
Classifier: Development Status :: 3 - Alpha
Classifier: Intended Audience :: Developers
Classifier: Topic :: Software Development :: Build Tools
Classifier: License :: OSI Approved :: MIT License
Classifier: Programming Language :: Python :: 3.8
